django_string_externalization/__init__.py
django_string_externalization/html_util.py
django_string_externalization/text_entry_manager.py
django_string_externalization/text_maker.py
django_string_externalization/text_watcher.py
django_string_externalization-0.31.dist-info/METADATA
django_string_externalization-0.31.dist-info/WHEEL
django_string_externalization-0.31.dist-info/top_level.txt
django_string_externalization-0.31.dist-info/RECORD
