Metadata-Version: 2.1
Name: django_string_externalization
Version: 0.31
Home-page: https://github.com/AlexCLeduc/django_string_externalization
Author: AlexCLeduc
Classifier: Programming Language :: Python :: 3
Classifier: License :: OSI Approved :: MIT License
Classifier: Operating System :: OS Independent
